smart_code/__init__.py
smart_code/analyzer.py
smart_code/cli.py
smart_code/codemod.py
smart_code/detectors.py
smart_code/patterns.json
smart_code/patterns.py
smart_code/suggest.py
smart_code/suggestor.py
smart_code-0.5.0.dist-info/entry_points.txt
smart_code-0.5.0.dist-info/LICENSE
smart_code-0.5.0.dist-info/METADATA
smart_code-0.5.0.dist-info/WHEEL
smart_code-0.5.0.dist-info/RECORD
