Metadata-Version: 2.3
Name: smart_code
Version: 0.5.0
Summary: Static analysis tool for Python code optimization suggestions
Author: mingchi.sun
Author-email: marshalx9@163.com
Requires-Python: >=3.8
Classifier: Programming Language :: Python :: 3
Classifier: Programming Language :: Python :: 3.8
Classifier: Programming Language :: Python :: 3.9
Classifier: Programming Language :: Python :: 3.10
Classifier: Programming Language :: Python :: 3.11
Classifier: Programming Language :: Python :: 3.12
Classifier: Programming Language :: Python :: 3.13
Requires-Dist: libcst
Requires-Dist: mypy
